
<MySource_AREA id_name="left_col_menu_prefix_dynamic" design_area="nest_content" print="no"><MySource_SET name="type_codes" value="page" /></MySource_AREA>

<MySource_AREA id_name="left_col_menu_prefix_dynamic_switch" design_area="show_if" print="no">
	<MySource_SET name="condition" value="keyword_regexp" />
	<MySource_SET name="condition_keyword" value="asset_metadata__content_menu_prefix" />
	<MySource_SET name="condition_keyword_match" value="[<>a-z]+" />
	<MySource_THEN>
															<!-- START: #left_col_menu_prefix_via_metadata -->
<MySource_PRINT id_name="left_col_menu_prefix_via_metadata" />
															<!--  END:  #left_col_menu_prefix_via_metadata -->
	</MySource_THEN>
	<MySource_ELSE>
															<!-- START: #left_col_menu_prefix_dynamic -->
<MySource_PRINT id_name="left_col_menu_prefix_dynamic" />
															<!--  END:  #left_col_menu_prefix_dynamic -->
	</MySource_ELSE>
</MySource_AREA>

								<!-- START show_if: #HIDE_left_col -->
<MySource_AREA id_name="HIDE_left_col" design_area="show_if">
	<MySource_SET name="condition" value="keyword_regexp" />
	<MySource_SET name="condition_keyword" value="asset_metadata_hide_content_menu" />
	<MySource_SET name="condition_keyword_match" value="hide-content-menu" />
	<MySource_THEN>

									<!-- (left) content menu removed by metadata field "hide_content-menu" = "hide-content-menu" -->

	</MySource_THEN>
	<MySource_ELSE>
								<div class="<MySource_PRINT id_name="left_col_metadata_hidden_right" />
									secondary-navigation-container hidden-print" id="aside-left-col">
									<aside class="aside-left
										<MySource_PRINT id_name="metadata_lhs_menu_syblings_show_hide" />">
										<nav id="secondary-navigation" class="secondary-navigation
											-m-

											<MySource_PRINT id_name="metadata_lhs_menu_show_files" />

											-m-

											<MySource_PRINT id_name="metadata_lhs_menu_show_news_items" />

											-m-

											<MySource_PRINT id_name="metadata_lhs_menu_show_events" />

											-m-

											<MySource_PRINT id_name="lhs_menu_level_1" />

											-m-

											<MySource_PRINT id_name="lhs_menu_level_2" />

											-m-

											<MySource_PRINT id_name="lhs_menu_level_3" />

											-m-

											<MySource_PRINT id_name="lhs_menu_switch" />">

											<!-- START menu_normal: #left_col_static_level_menu -->
<MySource_PRINT id_name="left_col_static_level_menu" />
											<!--  END  menu_normal: #left_col_static_level_menu -->

											<ul id="menu_dynamic">
												<li class="Hierarchy">
													<!-- START show_if: #left_col_menu_prefix_dynamic_switch -->
<MySource_PRINT id_name="left_col_menu_prefix_dynamic_switch" />
													<!--  END  show_if: #left_col_menu_prefix_dynamic_switch -->



													<!-- START asset_lineage: #left_col_single_parent_list -->
<MySource_PRINT id_name="left_col_single_parent_list" />
													<!--  END  asset_lineage: #left_col_single_parent_list -->

													<!-- START menu_normal: #left_col_dynamic_level_menu -->
<MySource_PRINT id_name="left_col_dynamic_level_menu" />
													<!--  END  menu_normal: #left_col_dynamic_level_menu -->
												</li>
											</ul>
										</nav>
									</aside>
								</div>
	</MySource_ELSE>
</MySource_AREA>
								<!--  END  show_if: #HIDE_left_col -->

